setup.cfg
setup.py
zenoss.py
zenoss.egg-info/PKG-INFO
zenoss.egg-info/SOURCES.txt
zenoss.egg-info/dependency_links.txt
zenoss.egg-info/pbr.json
zenoss.egg-info/top_level.txt