Metadata-Version: 1.0
Name: zenoss
Version: 0.6.2
Summary: Module to work with the Zenoss JSON API.
Home-page: https://github.com/iamseth/python-zenoss
Author: Seth Miller
Author-email: seth@sethmiller.me
License: UNKNOWN
Keywords: zenoss,api,json,rest
Platform: UNKNOWN
